[{"line":1,"elements":[{"start_timestamp":"2022-04-07T22:10:21.879Z","before":[{"result":{"duration":5935296900,"status":"passed"},"match":{"location":"StepDef.Hook.innitialize()"}}],"line":17,"name":"Calculate Mortgage rate with given values and default values","description":"","id":"mortgage-claculator-test-datatable;calculate-mortgage-rate-with-given-values-and-default-values;;2","after":[{"result":{"duration":6014018500,"status":"passed"},"match":{"location":"StepDef.Hook.teardown()"}}],"type":"scenario","keyword":"Scenario Outline","steps":[{"result":{"duration":5195085200,"status":"passed"},"line":4,"name":"I am on the Mortgage Calculator website","match":{"location":"StepDef.MortageCalculatorStepDefs.i_am_on_the_mortgage_calculator_website()"},"keyword":"Given "},{"result":{"duration":2949770900,"status":"passed"},"line":5,"name":"I enter the following","match":{"location":"StepDef.MortageCalculatorStepDefs.i_enter_the_following(java.util.List<java.util.List<java.lang.String>>)"},"rows":[{"cells":["field","Value"]},{"cells":["homeValue","50000"]},{"cells":["downPayment","20000"]},{"cells":["interestRate","5"]},{"cells":["loanTerm","25"]},{"cells":["startMonth","Sep"]},{"cells":["startYear","2020"]}],"keyword":"When "},{"result":{"status":"passed"},"line":13,"name":"accept default value for all the remaining values","match":{"location":"StepDef.MortageCalculatorStepDefs.accept_default_value_for_all_the_remaining_values()"},"keyword":"And "},{"result":{"duration":153195400,"status":"passed"},"line":14,"name":"I should get mortage offer with \"$458.71\", \"$20,000.00\", \"40.00%\", \"Aug, 2045\", \"$22,613.10\" and \"$203.00\"","match":{"arguments":[{"val":"\"$458.71\"","offset":32},{"val":"\"$20,000.00\"","offset":43},{"val":"\"40.00%\"","offset":57},{"val":"\"Aug, 2045\"","offset":67},{"val":"\"$22,613.10\"","offset":80},{"val":"\"$203.00\"","offset":97}],"location":"StepDef.GeneralStepDef.i_should_get_mortage_offer_with_and(java.lang.String,java.lang.String,java.lang.String,java.lang.String,java.lang.String,java.lang.String)"},"keyword":"Then "}],"tags":[{"name":"@F1"}]}],"name":"Mortgage claculator test DATATABLE","description":"","id":"mortgage-claculator-test-datatable","keyword":"Feature","uri":"file:src/main/resources/featureFiles/MortageCalculator.feature","tags":[]}]